[
  {
    "id": 1754776137405,
    "title": "Editorial news & latest pictures from Newsweek.com",
    "url": "https://www.newsweek.com/topic/editorial",
    "normalizedUrl": "https://www.newsweek.com/topic/editorial",
    "platform": "Newsweek",
    "date": "2025-08-09",
    "snippet": "2 days ago ... Freelancers Need Union Protections. Success in unionizing will set a new precedent in the editorial world. By Daniel Lehewych On 8/6/21 at 12:30 ...",
    "urlSlug": "/archive/newsweek/editorial-news-latest-pictures-from-newsweek-com",
    "type": "OpinionNewsArticle",
    "topics": [
      "Politics & Society"
    ],
    "fingerprint": "e5350a01f8bec7316016bfc1561e4a6a7b8418c9a6e1b7f318230ad7e58f1f87",
    "version": 1,
    "discoveredAt": "2025-08-09T21:48:57.405Z",
    "emailSubject": "SOV-ARCH NEW · Newsweek · \"Editorial news & latest pictures from Newsweek.com\" · 2025-08-09",
    "headerCode": "<meta name=\"robots\" content=\"noindex, follow\">\n<script type=\"application/ld+json\">\n{\n  \"@context\": \"https://schema.org\",\n  \"@type\": \"OpinionNewsArticle\",\n  \"@id\": \"https://daniellehewych.org/archive/newsweek/editorial-news-latest-pictures-from-newsweek-com\",\n  \"headline\": \"Editorial news & latest pictures from Newsweek.com\",\n  \"description\": \"2 days ago ... Freelancers Need Union Protections. Success in unionizing will set a new precedent in the editorial world. By Daniel Lehewych On 8/6/21 at 12:30 ...\",\n  \"image\": \"https://images.squarespace-cdn.com/content/v1/5ff1bf1e8500a82fe9da19d6/e7b2be48-1fc7-4ff1-8d5b-15ff408f3502/image_123655411.jpg?format=1200w\",\n  \"author\": {\n    \"@id\": \"https://daniellehewych.org/#daniel-lehewych\"\n  },\n  \"datePublished\": \"2025-08-09T00:00:00Z\",\n  \"dateCreated\": \"2025-08-09T00:00:00Z\",\n  \"dateModified\": \"2025-08-09T00:00:00Z\",\n  \"publisher\": {\n    \"@type\": \"Organization\",\n    \"name\": \"Newsweek\",\n    \"logo\": {\n      \"@type\": \"ImageObject\",\n      \"url\": \"https://www.newsweek.com/favicon.ico\",\n      \"width\": 32,\n      \"height\": 32\n    }\n  },\n  \"sameAs\": \"https://www.newsweek.com/topic/editorial\",\n  \"url\": \"https://daniellehewych.org/archive/newsweek/editorial-news-latest-pictures-from-newsweek-com\",\n  \"isPartOf\": {\n    \"@type\": \"Blog\",\n    \"name\": \"Daniel Lehewych Shadow Archive\",\n    \"url\": \"https://daniellehewych.org/archive/\",\n    \"author\": {\n      \"@id\": \"https://daniellehewych.org/#daniel-lehewych\"\n    }\n  },\n  \"mainEntityOfPage\": {\n    \"@type\": \"WebPage\",\n    \"@id\": \"https://daniellehewych.org/archive/newsweek/editorial-news-latest-pictures-from-newsweek-com\"\n  },\n  \"wordCount\": 1000,\n  \"inLanguage\": \"en-US\",\n  \"copyrightHolder\": {\n    \"@id\": \"https://daniellehewych.org/#daniel-lehewych\"\n  },\n  \"copyrightYear\": \"2025\",\n  \"license\": \"https://creativecommons.org/licenses/by-nc-nd/4.0/\",\n  \"backstory\": \"Contemporary analysis and expert commentary\",\n  \"printEdition\": \"Newsweek Digital\",\n  \"speakable\": {\n    \"@type\": \"SpeakableSpecification\",\n    \"cssSelector\": [\n      \".article-content p:first-of-type\",\n      \"h1\",\n      \".article-summary\"\n    ]\n  },\n  \"keywords\": \"politics & society\"\n}\n</script>",
    "topicBlockCode": "<!-- Topic Clustering Block - Add to page body -->\n<script type=\"application/ld+json\">\n{\n  \"@context\": \"https://schema.org\",\n  \"@type\": \"WebPage\",\n  \"@id\": \"https://daniellehewych.org/archive/newsweek/editorial-news-latest-pictures-from-newsweek-com\",\n  \"about\": [\n    {\n      \"@type\": \"Thing\",\n      \"name\": \"Politics & Society\"\n    }\n  ],\n  \"keywords\": \"politics & society\",\n  \"mentions\": [],\n  \"breadcrumb\": {\n    \"@type\": \"BreadcrumbList\",\n    \"itemListElement\": [\n      {\n        \"@type\": \"ListItem\",\n        \"position\": 1,\n        \"name\": \"Daniel Lehewych\",\n        \"item\": \"https://daniellehewych.org/\"\n      },\n      {\n        \"@type\": \"ListItem\",\n        \"position\": 2,\n        \"name\": \"Editorial news & latest pictures from Newsweek.com\",\n        \"item\": \"https://daniellehewych.org/archive/newsweek/editorial-news-latest-pictures-from-newsweek-com\"\n      }\n    ]\n  }\n}\n</script>",
    "relatedBlockCode": "<!-- Related Articles Block - Add to page body -->\n<script type=\"application/ld+json\">\n{\n  \"@context\": \"https://schema.org\",\n  \"@type\": \"ItemList\",\n  \"name\": \"Related Articles by Daniel Lehewych\",\n  \"description\": \"Add related articles after creating shadow page\",\n  \"numberOfItems\": 0,\n  \"itemListElement\": []\n}\n</script>",
    "pageContent": "<div class=\"shadow-archive-entry\" style=\"font-family: 'Merriweather', serif; max-width: 800px; margin: 0 auto; padding: 40px 20px;\">\n  <div style=\"background: #f0f0f0; padding: 20px; border-radius: 8px; margin-bottom: 30px;\">\n    <p style=\"margin: 0; font-size: 14px; color: #666;\">\n      <strong>Shadow Archive Entry</strong> | Not Indexed | For Attribution Only\n    </p>\n  </div>\n\n  <h1 style=\"font-family: 'Inter', sans-serif; font-size: 32px; line-height: 1.3; margin-bottom: 20px;\">\n    Editorial news &amp; latest pictures from Newsweek.com\n  </h1>\n\n  <div style=\"border-bottom: 1px solid #e0e0e0; padding-bottom: 20px; margin-bottom: 30px;\">\n    <p style=\"margin: 5px 0; color: #666;\">\n      <strong>Originally Published:</strong> 2025-08-09 on Newsweek<br>\n      <strong>Original URL:</strong> <a href=\"https://www.newsweek.com/topic/editorial\" rel=\"canonical\" style=\"color: #4F7CAC;\">View on Newsweek</a><br>\n      <strong>Author:</strong> Daniel Lehewych\n    </p>\n  </div>\n\n  <div class=\"article-content\" style=\"font-size: 18px; line-height: 1.8;\">\n    <p><em>[Article content to be added]</em></p>\n  </div>\n\n  <div style=\"margin-top: 50px; padding-top: 30px; border-top: 1px solid #e0e0e0;\">\n    <p style=\"font-size: 14px; color: #666; text-align: center;\">\n      This content is archived for attribution and reference purposes only.<br>\n      Copyright © 2025 Daniel Lehewych. All rights reserved.\n    </p>\n  </div>\n</div>",
    "bibliographyEntry": {
      "@type": "ListItem",
      "position": 374,
      "item": {
        "@type": "Article",
        "@id": "https://daniellehewych.org/archive/newsweek/editorial-news-latest-pictures-from-newsweek-com",
        "name": "Editorial news & latest pictures from Newsweek.com",
        "description": "2 days ago ... Freelancers Need Union Protections. Success in unionizing will set a new precedent in the editorial world. By Daniel Lehewych On 8/6/21 at 12:30 ...",
        "url": "https://www.newsweek.com/topic/editorial",
        "datePublished": "2025-08-09T00:00:00Z",
        "author": {
          "@id": "https://daniellehewych.org/#daniel-lehewych"
        },
        "isAccessibleForFree": true,
        "image": "https://images.squarespace-cdn.com/content/v1/5ff1bf1e8500a82fe9da19d6/e7b2be48-1fc7-4ff1-8d5b-15ff408f3502/image_123655411.jpg?format=1200w",
        "isPartOf": {
          "@type": [
            "Periodical",
            "CreativeWork"
          ],
          "name": "Newsweek",
          "issn": ""
        },
        "sameAs": [
          "https://www.newsweek.com/topic/editorial",
          "https://daniellehewych.org/archive/newsweek/editorial-news-latest-pictures-from-newsweek-com"
        ]
      }
    }
  }
]